almaflow/__init__.py
almaflow/_state.py
almaflow/_transition.py
almaflow-0.2.3.dist-info/licenses/LICENSE
almaflow-0.2.3.dist-info/METADATA
almaflow-0.2.3.dist-info/WHEEL
almaflow-0.2.3.dist-info/top_level.txt
almaflow-0.2.3.dist-info/RECORD
