Metadata-Version: 2.4
Name: almaflow
Version: 0.2.3
Author: aturkenov
License-Expression: MIT
Requires-Python: >=3.12
License-File: LICENSE
Requires-Dist: almanet>=1.3.2
Provides-Extra: testing
Requires-Dist: pytest>=8.3.5; extra == "testing"
Requires-Dist: pytest-asyncio>=0.26.0; extra == "testing"
Requires-Dist: pytest-cov>=6.1.1; extra == "testing"
Dynamic: license-file
